{
    "Specials": [
        {
            "ID": "Weapon_Gauss_Gauss_0-STOCK",
            "Type": "Weapon",
            "DiscountModifier": 1,
            "Count" : 0,
			"Weight": 1
        },
		{
            "ID": "Weapon_Laser_MediumLaser_3-Magna",
            "Type": "Weapon",
            "DiscountModifier": 1,
            "Count": 0,
			"Weight": 1
        },
	    {
            "ID": "Weapon_Laser_MediumLaser_3-Ceres_Arms",
            "Type": "Weapon",
            "DiscountModifier": 1,
            "Count": 0,
			"Weight": 1
        },
		{
            "ID": "Weapon_PPC_PPC_3-Diverse_Optics",
            "Type": "Weapon",
            "DiscountModifier": 1,
            "Count": 0,
			"Weight": 1
        },
	    {
            "ID": "Weapon_PPC_PPC_3-Tiegart",
            "Type": "Weapon",
            "DiscountModifier": 1,
            "Count": 0,
			"Weight": 1
        },
	    {
            "ID": "Weapon_Flamer_Flamer_3-Zippo",
            "Type": "Weapon",
            "DiscountModifier": 1,
            "Count": 0,
			"Weight": 1
        },
		{
            "ID": "Weapon_MachineGun_MachineGun_1-Mydron",
            "Type": "Weapon",
            "DiscountModifier": 1,
            "Count": 0,
			"Weight": 1
        },
		
		
		
        {
            "ID": "Weapon_Autocannon_AC20_1-Federated",
            "Type": "Weapon",
            "DiscountModifier": 1,
            "Count": 0,
			"Weight" : 1
        },
        {
            "ID": "Weapon_Autocannon_AC2_1-Federated",
            "Type": "Weapon",
            "DiscountModifier": 1,
            "Count": 0,
			"Weight": 1
        },
        {
            "ID": "Weapon_Autocannon_AC5_1-Federated",
            "Type": "Weapon",
            "DiscountModifier": 1,
            "Count": 0,
			"Weight": 1
        },
        {
            "ID": "Weapon_Autocannon_AC5_2-Mydron",
            "Type": "Weapon",
            "DiscountModifier": 1,
            "Count": 0,
			"Weight": 1
        },
        {
            "ID": "Weapon_Laser_LargeLaser_1-ExoStar",
            "Type": "Weapon",
            "DiscountModifier": 1,
            "Count": 0,
			"Weight": 1
        },
        {
            "ID": "Weapon_Laser_MediumLaser_1-ExoStar",
            "Type": "Weapon",
            "DiscountModifier": 1,
            "Count": 0,
			"Weight": 1
        },
        {
            "ID": "Weapon_PPC_PPC_1-Tiegart",
            "Type": "Weapon",
            "DiscountModifier": 1,
            "Count": 0,
			"Weight": 1
        },
        {
            "ID": "Weapon_LRM_LRM10_1-LongFire",
            "Type": "Weapon",
            "DiscountModifier": 1,
            "Count": 0,
			"Weight": 1
        },
        {
            "ID": "Weapon_LRM_LRM15_1-LongFire",
            "Type": "Weapon",
            "DiscountModifier": 1,
            "Count": 0,
			"Weight": 1
        },
        {
            "ID": "Weapon_LRM_LRM20_1-LongFire",
            "Type": "Weapon",
            "DiscountModifier": 1,
            "Count": 0,
			"Weight": 1
        },
        {
            "ID": "Weapon_LRM_LRM5_1-LongFire",
            "Type": "Weapon",
            "DiscountModifier": 1,
            "Count": 0,
			"Weight": 1
        },
		{
            "ID": "Weapon_Autocannon_AC10_1-Imperator",
            "Type": "Weapon",
            "DiscountModifier": 1,
            "Count": 0,
			"Weight": 1
        },
        {
            "ID": "Weapon_Autocannon_AC20_1-Imperator",
            "Type": "Weapon",
            "DiscountModifier": 1,
            "Count": 0,
			"Weight": 1
        },
        {
            "ID": "Weapon_Autocannon_AC2_2-Imperator",
            "Type": "Weapon",
            "DiscountModifier": 1,
            "Count": 0,
			"Weight": 1
        },
        {
            "ID": "Weapon_Autocannon_AC5_1-Imperator",
            "Type": "Weapon",
            "DiscountModifier": 1,
            "Count": 0,
			"Weight": 1
        },
        {
            "ID": "Weapon_LRM_LRM10_2-Zeus",
            "Type": "Weapon",
            "DiscountModifier": 1,
            "Count": 0,
			"Weight": 1
        },
        {
            "ID": "Weapon_LRM_LRM15_2-Zeus",
            "Type": "Weapon",
            "DiscountModifier": 1,
            "Count": 0,
			"Weight": 1
        },
        {
            "ID": "Weapon_LRM_LRM20_2-Zeus",
            "Type": "Weapon",
            "DiscountModifier": 1,
            "Count": 0,
			"Weight": 1
        },
        {
            "ID": "Weapon_LRM_LRM5_2-Zeus",
            "Type": "Weapon",
            "DiscountModifier": 1,
            "Count": 0,
			"Weight": 1
        },
        {
            "ID": "Weapon_Laser_LargeLaser_2-Magna",
            "Type": "Weapon",
            "DiscountModifier": 1,
            "Count": 0,
			"Weight": 1
        },
        {
            "ID": "Weapon_Laser_MediumLaser_1-Magna",
            "Type": "Weapon",
            "DiscountModifier": 1,
            "Count": 0,
			"Weight": 1
        },
        {
            "ID": "Weapon_Laser_SmallLaser_1-Magna",
            "Type": "Weapon",
            "DiscountModifier": 1,
            "Count": 0,
			"Weight": 1
        },
        {
            "ID": "Weapon_SRM_SRM2_1-Irian",
            "Type": "Weapon",
            "DiscountModifier": 1,
            "Count": 0,
			"Weight": 1
        },
        {
            "ID": "Weapon_SRM_SRM4_1-Irian",
            "Type": "Weapon",
            "DiscountModifier": 1,
            "Count": 0,
			"Weight": 1
        },
        {
            "ID": "Weapon_SRM_SRM6_1-Irian",
            "Type": "Weapon",
            "DiscountModifier": 1,
            "Count": 0,
			"Weight": 1
        },
        {
            "ID": "Weapon_Flamer_Flamer_1-Hotshot",
            "Type": "Weapon",
            "DiscountModifier": 1,
            "Count": 0,
			"Weight": 1
        },
        {
            "ID": "Weapon_LRM_LRM10_1-Delta",
            "Type": "Weapon",
            "DiscountModifier": 1,
            "Count": 0,
			"Weight": 1
        },
        {
            "ID": "Weapon_LRM_LRM15_1-Delta",
            "Type": "Weapon",
            "DiscountModifier": 1,
            "Count": 0,
			"Weight": 1
        },
        {
            "ID": "Weapon_LRM_LRM20_1-Delta",
            "Type": "Weapon",
            "DiscountModifier": 1,
            "Count": 0,
			"Weight": 1
        },
        {
            "ID": "Weapon_LRM_LRM5_1-Delta",
            "Type": "Weapon",
            "DiscountModifier": 1,
            "Count": 0,
			"Weight": 1
        },
        {
            "ID": "Weapon_Laser_LargeLaser_1-Diverse_Optics",
            "Type": "Weapon",
            "DiscountModifier": 1,
            "Count": 0,
			"Weight": 1
        },
        {
            "ID": "Weapon_Laser_MediumLaser_2-Diverse_Optics",
            "Type": "Weapon",
            "DiscountModifier": 1,
            "Count": 0,
			"Weight": 1
        },
        {
            "ID": "Weapon_Laser_SmallLaser_1-Diverse_Optics",
            "Type": "Weapon",
            "DiscountModifier": 1,
            "Count": 0,
			"Weight": 1
        },
        {
            "ID": "Weapon_PPC_PPC_1-Donal",
            "Type": "Weapon",
            "DiscountModifier": 1,
            "Count": 0,
			"Weight": 1
        }		
    ]
}